resources_rc.py
mauspaf/__init__.py
mauspaf/application.py
mauspaf/core/__init__.py
mauspaf/core/mauspaf.py
mauspaf/core/misc.py
mauspaf/generated/__init__.py
mauspaf/generated/aboutwindow.py
mauspaf/generated/dl_partinfo.py
mauspaf/generated/dw_maintree.py
mauspaf/generated/dw_masslibrary.py
mauspaf/generated/dw_parteditor.py
mauspaf/generated/dw_plot.py
mauspaf/generated/mainwindow.py
mauspaf/guifun/__init__.py
mauspaf/guifun/inner.py
mauspaf/guifun/io.py
mauspaf/guifun/masslib.py
mauspaf/guifun/misc.py
mauspaf/masslibrary/__init__.py
mauspaf/masslibrary/aircraft.py
mauspaf/masslibrary/misc.py
mauspaf/masslibrary/shells.py
mauspaf/masslibrary/solids.py
mauspaf/masslibrary/thinrods.py
mauspaf/ui/__init__.py
mauspaf/ui/aboutwindow.py
mauspaf/ui/dw_maintree.py
mauspaf/ui/dw_masslibrary.py
mauspaf/ui/dw_parteditor.py
mauspaf/ui/mainwindow.py
mauspaf/ui/partinfo.py
mauspaf/widgets/__init__.py
mauspaf/widgets/qcomboboxes.py
mauspaf/widgets/qlineedits.py
mauspaf/widgets/qpushbuttons.py
mauspaf-0.0.4.dist-info/LICENSE
mauspaf-0.0.4.dist-info/METADATA
mauspaf-0.0.4.dist-info/WHEEL
mauspaf-0.0.4.dist-info/entry_points.txt
mauspaf-0.0.4.dist-info/top_level.txt
mauspaf-0.0.4.dist-info/RECORD
