Metadata-Version: 2.1
Name: mauspaf
Version: 0.0.4
Summary: Mass properties analysis.
Home-page: https://gitlab.com/mnn/mauspaf
Author: M. Nuño
Author-email: mnunos@outlook.com
Project-URL: Documentation, https://mnn.gitlab.io/mauspaf/
Project-URL: Source, https://gitlab.com/mnn/mauspaf
Project-URL: Bug Reports, https://gitlab.com/mnn/mauspaf/-/issues
Classifier: Development Status :: 4 - Beta
Classifier: Intended Audience :: Science/Research
Classifier: License :: OSI Approved :: GNU General Public License v3 (GPLv3)
Classifier: Programming Language :: Python
Requires-Python: >=3.6
License-File: LICENSE
Requires-Dist: numpy
Requires-Dist: matplotlib
Requires-Dist: PyQt5
Requires-Dist: sympy
Requires-Dist: scipy
Requires-Dist: plotly
Requires-Dist: pandas
Requires-Dist: uncertain
Requires-Dist: unitc
